poetry_scripts/__init__.py
poetry_scripts-0.0.1.dist-info/entry_points.txt
poetry_scripts-0.0.1.dist-info/WHEEL
poetry_scripts-0.0.1.dist-info/METADATA
poetry_scripts-0.0.1.dist-info/RECORD
