Metadata-Version: 2.1
Name: poetry-scripts
Version: 0.0.1
Summary: 
Author: Trim21
Author-email: i@trim21.me
Requires-Python: >=3.6.2,<4.0.0
Classifier: Programming Language :: Python :: 3
Classifier: Programming Language :: Python :: 3.7
Classifier: Programming Language :: Python :: 3.8
Classifier: Programming Language :: Python :: 3.9
Classifier: Programming Language :: Python :: 3.10
Requires-Dist: poetry (>=1.2.0a1,<2.0.0)
